gitpatrol
lib
