Metadata-Version: 1.1
Name: gitpatrol
Version: 0.0.2
Summary: Flexible Git Pre-Commit Hooks
Home-page: https://github.com/artburkart/gitpatrol
Author: Arthur Burkart
Author-email: artburkart@gmail.com
License: MIT
Keywords: git development version control gitpatrol patrol
Platform: UNKNOWN
Classifier: Development Status :: 3 - Alpha
Classifier: Intended Audience :: Developers
Classifier: Topic :: Software Development :: Version Control
Classifier: License :: OSI Approved :: MIT License
Classifier: Programming Language :: Python :: 2.7
